mml_similarity/__init__.py
mml_similarity/activate.py
mml_similarity/configs/__init__.py
mml_similarity/configs/distance/emd.yaml
mml_similarity/configs/distance/ens.yaml
mml_similarity/configs/distance/fed.yaml
mml_similarity/configs/distance/fid.yaml
mml_similarity/configs/distance/kld.yaml
mml_similarity/configs/distance/mmd.yaml
mml_similarity/configs/distance/semantic.yaml
mml_similarity/configs/mode/similarity.yaml
mml_similarity/configs/plotting/distance.yaml
mml_similarity/configs/plotting/kam.yaml
mml_similarity/configs/plotting/tsne.yaml
mml_similarity/configs/sampling/extraction_default.yaml
mml_similarity/configs/sampling/extraction_minimal.yaml
mml_similarity/configs/search_space/fed_search.yaml
mml_similarity/configs/search_space/mmd_search.yaml
mml_similarity/scripts/__init__.py
mml_similarity/scripts/abstract_task_distance_scheduler.py
mml_similarity/scripts/ensemble_scheduler.py
mml_similarity/scripts/feature_distances.py
mml_similarity/scripts/fed_scheduler.py
mml_similarity/scripts/fisher.py
mml_similarity/scripts/sample_based_scheduler.py
mml_similarity/scripts/semantic_scheduler.py
mml_similarity/scripts/vector_distances.py
mml_similarity/visualization/__init__.py
mml_similarity/visualization/plot_2D.py
mml_similarity-0.5.3.dist-info/licenses/LICENSE.txt
mml_similarity-0.5.3.dist-info/METADATA
mml_similarity-0.5.3.dist-info/WHEEL
mml_similarity-0.5.3.dist-info/entry_points.txt
mml_similarity-0.5.3.dist-info/top_level.txt
mml_similarity-0.5.3.dist-info/RECORD
